<data><id>oai:pangaea.de:doi:10.1594/PANGAEA.883993</id><md:MetaData/md:citation/md:title>Snow density of core EG16_LTW1 in snow trench LTW at the EGRIP field site, Greenland</md:MetaData/md:citation/md:title><md:MetaData/md:citation/md:supplementTo/md:title /><md:MetaData/md:abstract /><md:MetaData/md:project/md:label>AWI_Glac</md:MetaData/md:project/md:label><md:MetaData/md:event/md:label>Greenland_LTX</md:MetaData/md:event/md:label><md:MetaData/md:event/md:comment /><md:MetaData/md:license/md:label>CC-BY-3.0</md:MetaData/md:license/md:label><md:MetaData/md:additionalSearchableContent /><md:MetaData/md:reference/md:title /><date>2017-12-12T10:29:32</date></data>