<data><id>oai:pangaea.de:doi:10.1594/PANGAEA.596322</id><md:MetaData/md:citation/md:title>Tree-ring measurements of Abies borisii-regis (King Boris fir) from sample PANET-32</md:MetaData/md:citation/md:title><md:MetaData/md:citation/md:supplementTo/md:title /><md:MetaData/md:abstract /><md:MetaData/md:project/md:label>NHD/WSL</md:MetaData/md:project/md:label><md:MetaData/md:event/md:label>PANET</md:MetaData/md:event/md:label><md:MetaData/md:event/md:comment>Exposition N, Slope 30 deg, Geology: Kristalliner Schiefer, Tree line 1500 m, av. Tree height 25 m, Tree cover 10%, Herb cover 5%, Vegatation type: Abietetum borisii-regis, Film number: 647A</md:MetaData/md:event/md:comment><md:MetaData/md:license/md:label>CC-BY-3.0</md:MetaData/md:license/md:label><md:MetaData/md:additionalSearchableContent /><md:MetaData/md:reference/md:title /><date>2007-01-25T20:13:18</date></data>