<data><id>oai:pangaea.de:doi:10.1594/PANGAEA.593361</id><md:MetaData/md:citation/md:title>Tree-ring measurements of Larix sibirica (Siberian larch) from sample KHADYTLA-201</md:MetaData/md:citation/md:title><md:MetaData/md:citation/md:supplementTo/md:title /><md:MetaData/md:abstract /><md:MetaData/md:project/md:label>NHD/WSL</md:MetaData/md:project/md:label><md:MetaData/md:event/md:label>KHADYTLA</md:MetaData/md:event/md:label><md:MetaData/md:event/md:comment>Slope 0 deg, Geology: Alluvium, Sand, Tree line -70 m, av. Tree height 15 m, Tree cover 15%, Shrub cover 80%, Herb cover 60%, Moss cover 100%, Vegatation type: Lockerer L&#228;/Fi-Wald, Moos, Str&#228;ucher, Film number: 878A</md:MetaData/md:event/md:comment><md:MetaData/md:license/md:label>CC-BY-3.0</md:MetaData/md:license/md:label><md:MetaData/md:additionalSearchableContent /><md:MetaData/md:reference/md:title /><date>2007-01-25T19:13:29</date></data>