<data><id>oai:pangaea.de:doi:10.1594/PANGAEA.742627</id><md:MetaData/md:citation/md:title>Physical oceanography from 120 CTD stations during POLARSTERN cruise ANT-XXII/2 (ISPOL)</md:MetaData/md:citation/md:title><md:MetaData/md:citation/md:supplementTo/md:title /><md:MetaData/md:abstract /><md:MetaData/md:project/md:label>AWI_PhyOce</md:MetaData/md:project/md:label><md:MetaData/md:event/md:label>PS67/005-1</md:MetaData/md:event/md:label><md:MetaData/md:event/md:comment>INST.:AWI, CTD-SN:T2685-C2325</md:MetaData/md:event/md:comment><md:MetaData/md:license/md:label>CC-BY-3.0</md:MetaData/md:license/md:label><md:MetaData/md:additionalSearchableContent /><md:MetaData/md:reference/md:title>Early summer thermohaline characteristics and mixing in the western Weddell Sea</md:MetaData/md:reference/md:title><date>2008-06-29T15:02:17</date></data>