<data><id>oai:pangaea.de:doi:10.1594/PANGAEA.695859</id><md:MetaData/md:citation/md:title>Basic and other measurements of radiation at station Toravere (2008-04)</md:MetaData/md:citation/md:title><md:MetaData/md:citation/md:supplementTo/md:title /><md:MetaData/md:abstract /><md:MetaData/md:project/md:label>BSRN</md:MetaData/md:project/md:label><md:MetaData/md:event/md:label>TOR</md:MetaData/md:event/md:label><md:MetaData/md:event/md:comment>BSRN station no: 9, Surface type: grass, Topography type: flat, rural, Horizon from 1999 to 2001-06: doi:10.1594/PANGAEA.671374, Horizon after 2001-06: doi:10.1594/PANGAEA.671373, Station scientist: Ain Kallis (kallis@aai.ee)</md:MetaData/md:event/md:comment><md:MetaData/md:license/md:label /><md:MetaData/md:additionalSearchableContent /><md:MetaData/md:reference/md:title>BSRN Station-to-archive file for station Toravere (2008-04)</md:MetaData/md:reference/md:title><date>2008-06-18T16:02:25</date></data>