<data><id>oai:pangaea.de:doi:10.1594/PANGAEA.381074</id><md:MetaData/md:citation/md:title>Radiosonde PS36/13036 during POLARSTERN cruise ARK-XI/1 on 1995-08-01 09:39h</md:MetaData/md:citation/md:title><md:MetaData/md:citation/md:supplementTo/md:title /><md:MetaData/md:abstract /><md:MetaData/md:project/md:label>AWI_Meteo</md:MetaData/md:project/md:label><md:MetaData/md:event/md:label>PS36/13036</md:MetaData/md:event/md:label><md:MetaData/md:event/md:comment /><md:MetaData/md:license/md:label>CC-BY-3.0</md:MetaData/md:license/md:label><md:MetaData/md:additionalSearchableContent /><md:MetaData/md:reference/md:title /><date>1997-02-14T20:02:41</date></data>