<data><id>oai:pangaea.de:doi:10.1594/PANGAEA.896284</id><md:MetaData/md:citation/md:title>LADCP current measurements during Maria S. Merian cruise MSM43</md:MetaData/md:citation/md:title><md:MetaData/md:citation/md:supplementTo/md:title /><md:MetaData/md:abstract /><md:MetaData/md:project/md:label>RACE</md:MetaData/md:project/md:label><md:MetaData/md:event/md:label>MSM43_213-1</md:MetaData/md:event/md:label><md:MetaData/md:event/md:comment>telemetry and recovery</md:MetaData/md:event/md:comment><md:MetaData/md:license/md:label /><md:MetaData/md:additionalSearchableContent /><md:MetaData/md:reference/md:title>North Atlantic Current and Labrador Sea Water Circulation in the Subpolar North Atlantic - Cruise No. MSM43 - May 25 - June 27, 2015 - St. John's (Canada) - Nuuk (Greenland)</md:MetaData/md:reference/md:title><date>2018-11-27T12:25:45</date></data>