<data><id>oai:pangaea.de:doi:10.1594/PANGAEA.230079</id><md:MetaData/md:citation/md:title>Geochemistry of suspended matter at station BP00-19</md:MetaData/md:citation/md:title><md:MetaData/md:citation/md:supplementTo/md:title /><md:MetaData/md:abstract /><md:MetaData/md:project/md:label>SIRRO</md:MetaData/md:project/md:label><md:MetaData/md:event/md:label>BP00-19</md:MetaData/md:event/md:label><md:MetaData/md:event/md:comment>CTD/RS/bucket/large volume sampler</md:MetaData/md:event/md:comment><md:MetaData/md:license/md:label>CC-BY-3.0</md:MetaData/md:license/md:label><md:MetaData/md:additionalSearchableContent /><md:MetaData/md:reference/md:title>Geochemical processes in the Yenisei River and Estuary</md:MetaData/md:reference/md:title><date>2003-01-18T10:07:50</date></data>