<data><id>oai:pangaea.de:doi:10.1594/PANGAEA.596792</id><md:MetaData/md:citation/md:title>Tree-ring measurements of Picea obovata (Sibirean spruce) from sample POLUPCOB-591</md:MetaData/md:citation/md:title><md:MetaData/md:citation/md:supplementTo/md:title /><md:MetaData/md:abstract /><md:MetaData/md:project/md:label>NHD/WSL</md:MetaData/md:project/md:label><md:MetaData/md:event/md:label>POLUPCOB</md:MetaData/md:event/md:label><md:MetaData/md:event/md:comment>Slope 0 deg, Geology: Alluvial deposits, av. Tree height 25 m, Tree cover 50%, Shrub cover 60%, Herb cover 10%, Moss cover 20%, Vegatation type: Spruce-larch-birch forest, Film number: 964A</md:MetaData/md:event/md:comment><md:MetaData/md:license/md:label>CC-BY-3.0</md:MetaData/md:license/md:label><md:MetaData/md:additionalSearchableContent /><md:MetaData/md:reference/md:title /><date>2007-01-26T16:53:03</date></data>