<data><id>oai:pangaea.de:doi:10.1594/PANGAEA.728738</id><md:MetaData/md:citation/md:title>(Appendix B) Varimax-rotated principal component loadings of ODP Site 120-748</md:MetaData/md:citation/md:title><md:MetaData/md:citation/md:supplementTo/md:title /><md:MetaData/md:abstract /><md:MetaData/md:project/md:label>ODP</md:MetaData/md:project/md:label><md:MetaData/md:event/md:label>120-748B</md:MetaData/md:event/md:label><md:MetaData/md:event/md:comment>25 cores, 225.1 m cored, 0 m drilled, 84.5 % recovery</md:MetaData/md:event/md:comment><md:MetaData/md:license/md:label>CC-BY-3.0</md:MetaData/md:license/md:label><md:MetaData/md:additionalSearchableContent /><md:MetaData/md:reference/md:title>Paleogene benthic foraminifers from the southern Indian Ocean (Kerguelen Plateau): biostratigraphy and paleoecology</md:MetaData/md:reference/md:title><date>1992-10-23T15:39:49</date></data>