<data><id>oai:pangaea.de:doi:10.1594/PANGAEA.858948</id><md:MetaData/md:citation/md:title>Experiment on asian green mussels (Perna viridis), West Java, Indonesia (April 2012 - November 2013): survival hypoxia after two months transplantation</md:MetaData/md:citation/md:title><md:MetaData/md:citation/md:supplementTo/md:title /><md:MetaData/md:abstract /><md:MetaData/md:project/md:label /><md:MetaData/md:event/md:label>Jakarta_Bay</md:MetaData/md:event/md:label><md:MetaData/md:event/md:comment /><md:MetaData/md:license/md:label>CC-BY-NC-SA-3.0</md:MetaData/md:license/md:label><md:MetaData/md:additionalSearchableContent /><md:MetaData/md:reference/md:title /><date>2016-03-16T10:03:55</date></data>