<data><id>oai:pangaea.de:doi:10.1594/PANGAEA.485002</id><md:MetaData/md:citation/md:title>Documentation of multicorer GeoB7831-2, tube 1</md:MetaData/md:citation/md:title><md:MetaData/md:citation/md:supplementTo/md:title /><md:MetaData/md:abstract /><md:MetaData/md:project/md:label>MARUM</md:MetaData/md:project/md:label><md:MetaData/md:event/md:label>GeoB7831-2</md:MetaData/md:event/md:label><md:MetaData/md:event/md:comment>8/8 , 4/4 tubes filled, no water sample / Project LamShArK PA492/14-1</md:MetaData/md:event/md:comment><md:MetaData/md:license/md:label /><md:MetaData/md:additionalSearchableContent /><md:MetaData/md:reference/md:title /><date>2006-07-21T11:08:52</date></data>