<data><id>oai:pangaea.de:doi:10.1594/PANGAEA.750214</id><md:MetaData/md:citation/md:title>Meteorological observations during La Perla cruise from Cartagena to Mahon started at 1822-08-17</md:MetaData/md:citation/md:title><md:MetaData/md:citation/md:supplementTo/md:title /><md:MetaData/md:abstract /><md:MetaData/md:project/md:label>CLIWOC</md:MetaData/md:project/md:label><md:MetaData/md:event/md:label>La_Perla_18220817_MS_1846</md:MetaData/md:event/md:label><md:MetaData/md:event/md:comment>Ship: La Perla (Fragata), Voyage: Cartagena - Mahon, 1st Observer: Jos&#233; de Juli&#225;n (Capitan)</md:MetaData/md:event/md:comment><md:MetaData/md:license/md:label>CC-BY-3.0</md:MetaData/md:license/md:label><md:MetaData/md:additionalSearchableContent /><md:MetaData/md:reference/md:title>CLIWOC: A Climatological Database for the World's Oceans 1750&#8211;1854 (and 10 more publications about CLIWOC results in the same volume)</md:MetaData/md:reference/md:title><date>2010-10-29T20:37:34</date></data>