<data><id>oai:pangaea.de:doi:10.1594/PANGAEA.739921</id><md:MetaData/md:citation/md:title>Pollen profile UBERLING, Grosses &#220;berling Schattseit-Moor, Austria</md:MetaData/md:citation/md:title><md:MetaData/md:citation/md:supplementTo/md:title /><md:MetaData/md:abstract /><md:MetaData/md:project/md:label /><md:MetaData/md:event/md:label>UBERLING</md:MetaData/md:event/md:label><md:MetaData/md:event/md:comment>Area: 12 ha. Almost untouched. Surrounding vegetation: Picea forest with Larix and Pinus cembra.</md:MetaData/md:event/md:comment><md:MetaData/md:license/md:label>CC-BY-NC-3.0</md:MetaData/md:license/md:label><md:MetaData/md:additionalSearchableContent /><md:MetaData/md:reference/md:title>Die Moore des Ost-Lungaues - Heutige Vegetation, Enstehung, Waldgeschichte ihrer Umgebung</md:MetaData/md:reference/md:title><date>2010-06-08T15:08:25</date></data>