<data><id>oai:pangaea.de:doi:10.1594/PANGAEA.422560</id><md:MetaData/md:citation/md:title>Silicate of sediment profile 7BC13</md:MetaData/md:citation/md:title><md:MetaData/md:citation/md:supplementTo/md:title /><md:MetaData/md:abstract /><md:MetaData/md:project/md:label>SINOPS</md:MetaData/md:project/md:label><md:MetaData/md:event/md:label>7BC13</md:MetaData/md:event/md:label><md:MetaData/md:event/md:comment /><md:MetaData/md:license/md:label>CC-BY-3.0</md:MetaData/md:license/md:label><md:MetaData/md:additionalSearchableContent /><md:MetaData/md:reference/md:title>Early diagenesis in sediments from the eastern equatorial Pacific, I. Pore water nutrient and carbonate results</md:MetaData/md:reference/md:title><date>2006-05-05T16:17:26</date></data>