<data><id>oai:pangaea.de:doi:10.1594/PANGAEA.885458</id><md:MetaData/md:citation/md:title>Lithology of sediment core CAMILLA2, Camillan Wood, Ireland</md:MetaData/md:citation/md:title><md:MetaData/md:citation/md:supplementTo/md:title /><md:MetaData/md:abstract /><md:MetaData/md:project/md:label /><md:MetaData/md:event/md:label>CAMILLA2</md:MetaData/md:event/md:label><md:MetaData/md:event/md:comment>Terrestrial soil mor humus. Physiography: basin. Surrounding vegetation: Blechno-Quercetum association. Local vegetation: Quercus pet, Ilex aqu., Taxus, Salix, Betula. Location: central part of the wood. Device: Russian corer (4 cm)</md:MetaData/md:event/md:comment><md:MetaData/md:license/md:label /><md:MetaData/md:additionalSearchableContent /><md:MetaData/md:reference/md:title>The vegetational history of the Killarney oak woods southwest Ireland: evidence from fine spatial resolution pollen analysis</md:MetaData/md:reference/md:title><date>2018-01-24T08:47:38</date></data>