<data><id>oai:pangaea.de:doi:10.1594/PANGAEA.895229</id><md:MetaData/md:citation/md:title>Middle Miocene benthic Nd isotopes of ODP Hole 189-1171C</md:MetaData/md:citation/md:title><md:MetaData/md:citation/md:supplementTo/md:title /><md:MetaData/md:abstract /><md:MetaData/md:project/md:label>ODP</md:MetaData/md:project/md:label><md:MetaData/md:event/md:label>189-1171C</md:MetaData/md:event/md:label><md:MetaData/md:event/md:comment>31 core, 274.8 m cored, 0 m drilled, 89.4 % recovery</md:MetaData/md:event/md:comment><md:MetaData/md:license/md:label>CC-BY-4.0</md:MetaData/md:license/md:label><md:MetaData/md:additionalSearchableContent /><md:MetaData/md:reference/md:title>Changes in Pacific Ocean circulation following the Miocene onset of permanent Antarctic ice cover</md:MetaData/md:reference/md:title><date>2018-10-12T10:01:48</date></data>