<data><id>oai:v1.datadryad.org:10255/dryad.123956</id><oai_dc:dc/dc:title>Landscape genetic input files</oai_dc:dc/dc:title><oai_dc:dc/dc:description>Input asci files of all environmental factors and PO- and PA-raw models for ResistanceGA. Also, PO- and PA-optim models included. Ordered by rank of landscape genetic optimization procedure.</oai_dc:dc/dc:description><oai_dc:dc/dc:subject>biodiverstiy|conservation|corridor|ecology|isolation|Reptiles</oai_dc:dc/dc:subject><date
>2016-08-19T13:28:31Z</date
></data>