<data><id>oai:v1.datadryad.org:10255/dryad.102551</id><oai_dc:dc/dc:title>Terrestrial arthropods of Steel Creek - Coleoptera</oai_dc:dc/dc:title><oai_dc:dc/dc:description>The beetles included within this data set were collected at Steel Creek, Buffalo National River, Newton County, Arkansas between April and December 2013 using a variety of collecting techniques.  The spreadsheet uses Darwin Core headings, which are defined in the ReadMe file.</oai_dc:dc/dc:description><oai_dc:dc/dc:subject>arthropod sampling|Malaise trap|pitfall trap|colored pan trap|Lindgren funnel trap|Berlese-Tullgren|state record|range expansion|endemic</oai_dc:dc/dc:subject><date
>2015-12-16T00:10:49Z</date
></data>