<data><id>oai:v1.datadryad.org:10255/dryad.80398</id><oai_dc:dc/dc:title>Growth parameters of ancestral and evolved lines</oai_dc:dc/dc:title><oai_dc:dc/dc:description>Growth parameters (e.g. growth rate, carrying capacity) extracted from growth curve fitting for each ancestral and evolved line when cultured in the selection environment (5gL-1 NaCl)</oai_dc:dc/dc:description><oai_dc:dc/dc:subject>Experimental evolution|Adaptation|Repeatability|Historical contingency|Stochasticity</oai_dc:dc/dc:subject><date
>2015-02-24T15:07:56Z</date
></data>