<data><id>oai:v1.datadryad.org:10255/dryad.100460</id><oai_dc:dc/dc:title>Flowering time, microsatellite and MS-AFLP data from apomictic dandelion</oai_dc:dc/dc:title><oai_dc:dc/dc:description>Apomictic clone members from common dandelion microspecies Taraxacum officinale 'Alatum' screened under common greenhouse environments for variation in microsatellites, methylation-sensitive AFLPs and flowering time.</oai_dc:dc/dc:description><oai_dc:dc/dc:subject>Contemporary Evolution|Ecological Genetics|Plant Mating Systems|Epigenetics</oai_dc:dc/dc:subject><date
>2015-11-26T02:33:29Z</date
></data>