<data><id>oai:v1.datadryad.org:10255/dryad.75975</id><oai_dc:dc/dc:title>amilFP597 exon 3 sequences</oai_dc:dc/dc:title><oai_dc:dc/dc:description>The chromophore coding sequences of RFP-related genes of A. millepora were amplified using genomic DNAof LR, MR and HR morphs as the template with primers designed to conserved regions within exon 3 .</oai_dc:dc/dc:description><oai_dc:dc/dc:subject>Adaptation|Climate Change|Cnidarians|Gene Structure and Function|Phenotypic Plasticity</oai_dc:dc/dc:subject><date
>2014-12-11T19:11:35Z</date
></data>