<data><id>oai:v1.datadryad.org:10255/dryad.18969</id><oai_dc:dc/dc:title>Dendrochronology study of fire history, Andrews Experimental Forest and vicinity, Oregon (Teensma thesis)</oai_dc:dc/dc:title><oai_dc:dc/dc:description>To describe the historical fire regime of the study area. To compare fire frequencies over different historical periods. To test whether fire regimes vary spatially according to landscape or topographic controls.</oai_dc:dc/dc:description><oai_dc:dc/dc:subject>Dendrochronology|Disturbance|Fire|Fire history|Fire regimes|Long-term Ecological Research (LTER)</oai_dc:dc/dc:subject><date
>2005-07-25</date
></data>