<data><id>0b350914-f65c-4104-957a-cad68ca42f3a</id><eml:eml/dataset/title>A new species of Quexua from southeastern Peru (Hymenoptera, Crabronidae)</eml:eml/dataset/title><eml:eml/dataset/abstract/para>This dataset contains the digitized treatments in Plazi based on the original journal article Bennett, Daniel J. (2011): A new species of Quexua from southeastern Peru (Hymenoptera, Crabronidae). ZooKeys 141: 65-70, DOI: http://dx.doi.org/10.3897/zookeys.141.1965, URL: http://dx.doi.org/10.3897/zookeys.141.1965</eml:eml/dataset/abstract/para><date>2011-01-01</date></data>