<data><id>12b053da-3ef4-4748-a22b-abeacee26742</id><eml:eml/dataset/title>Three new species of foetid Gymnopus in New Zealand</eml:eml/dataset/title><eml:eml/dataset/abstract/para>This dataset contains the digitized treatments in Plazi based on the original journal article Cooper, Jerry A., Leonard, Pat L. (2013): Three new species of foetid Gymnopus in New Zealand. MycoKeys 7: 31-44, DOI: http://dx.doi.org/10.3897/mycokeys.7.4710, URL: http://dx.doi.org/10.3897/mycokeys.7.4710</eml:eml/dataset/abstract/para><date>2013-01-01</date></data>