<data><id>161c718f-8356-4e0d-8d2e-cf7bbf20d490</id><eml:eml/dataset/title>A new species of Zetekella Drake from Ecuador with comments on Zetekella and Minitingis Barber (Heteroptera, Tingidae)</eml:eml/dataset/title><eml:eml/dataset/abstract/para>This dataset contains the digitized treatments in Plazi based on the original journal article Guidoti, Marcus, Guilbert, Eric (2018): A new species of Zetekella Drake from Ecuador with comments on Zetekella and Minitingis Barber (Heteroptera, Tingidae). ZooKeys 796: 291-299, DOI: http://dx.doi.org/10.3897/zookeys.796.23869, URL: http://dx.doi.org/10.3897/zookeys.796.23869</eml:eml/dataset/abstract/para><date>2018-01-01</date></data>