<data><id>18680b2b-84db-4d45-8acd-0b0e9467fb33</id><eml:eml/dataset/title>Digital Archives of Taiwan Malacofauna Database</eml:eml/dataset/title><eml:eml/dataset/abstract/para>The Taiwan Malacofauna Database includes information on 292 families, 3,818 species of Taiwan shells. The database consists of many sub-databases: &#8220;Checklist of Taiwan shells,&#8221; &#8220;Shell specimens from Taiwan,&#8221; &#8220;New species and new records of shells from Taiwan,&#8221; &#8220;The shells of world,&#8221; &#8220;Reference of shells,&#8221; &#8220;Shell middens in Taiwan,&#8221; &#8220;Shell fossils from Taiwan,&#8221; &#8220;Radula and ultrastructure of shells,&#8221; and &#8220;Chinese characters of shell.&#8221;</eml:eml/dataset/abstract/para><date>2014-03-25</date></data>