<data><id>1b7b0df0-2a82-4b61-9a9d-173697bfd207</id><eml:eml/dataset/title>New species of Anabarhynchus Macquart (Diptera: Therevidae) from arid and monsoon tropical Australia</eml:eml/dataset/title><eml:eml/dataset/abstract/para>This dataset contains the digitized treatments in Plazi based on the original journal article Ferguson, David J., Irwin, Michael E., Yeates, David K. (2013): New species of Anabarhynchus Macquart (Diptera: Therevidae) from arid and monsoon tropical Australia. Zootaxa 3680 (1): 55-95, DOI: http://dx.doi.org/10.11646/zootaxa.3680.1.5</eml:eml/dataset/abstract/para><date>2013-01-01</date></data>