<data><id>265fb13a-515a-47f6-84da-88b294e88798</id><eml:eml/dataset/title>Colecci&#243;n Ornitol&#243;gica Museo de Ciencias Naturales &#8220;Lorenzo Scaglia" (MMPOr) Mar del Plata, Argentina.</eml:eml/dataset/title><eml:eml/dataset/abstract/para>Colecci&#243;n de aves, en su mayor&#237;a son ejemplares del sudeste de la provincia de Buenos Aires.La colecci&#243;n originaria del recurso pertenece a un proyecto efectuado en la d&#233;cada del 1980, luego la colecci&#243;n se fue incrementando a partir de nuevos especimenes incorporados a trav&#233;s de apariciones ocasionales, ya sea por investigadores o p&#250;blico que trae material al museo para su consulta.</eml:eml/dataset/abstract/para><date>2019-08-17</date></data>