<data><id>2f3299e5-fd0d-45a3-a9e5-88c18adbbe58</id><eml:eml/dataset/title>Cochylis Treitschke in China: one new species and five new records (Lepidoptera, Tortricidae, Cochylini)</eml:eml/dataset/title><eml:eml/dataset/abstract/para>This dataset contains the digitized treatments in Plazi based on the original journal article Sun, Yinghui, Li, Houhun (2013): Cochylis Treitschke in China: one new species and five new records (Lepidoptera, Tortricidae, Cochylini). ZooKeys 258: 85-96, DOI: http://dx.doi.org/10.3897/zookeys.258.4108, URL: http://dx.doi.org/10.3897/zookeys.258.4108</eml:eml/dataset/abstract/para><date>2013-01-01</date></data>