<data><id>3d3c7ad3-5b3c-4a1e-9ac7-c3d5691b6db0</id><eml:eml/dataset/title>Two tropical species of Stephanotheca (Bryozoa, Cheilostomata, Lanceoporidae) from the Gulf of Carpentaria, Australia</eml:eml/dataset/title><eml:eml/dataset/abstract/para>This dataset contains the digitized treatments in Plazi based on the original journal article Cumming, Robyn L. (2015): Two tropical species of Stephanotheca (Bryozoa, Cheilostomata, Lanceoporidae) from the Gulf of Carpentaria, Australia. Zootaxa 3948 (2): 279-286, DOI: http://dx.doi.org/10.11646/zootaxa.3948.2.8</eml:eml/dataset/abstract/para><date>2015-01-01</date></data>