<data><id>459fcad7-286f-4273-854e-9020f9bbd042</id><eml:eml/dataset/title>New earthworm records from Turkey, with description of three new species (Oligochaeta: Lumbricidae)</eml:eml/dataset/title><eml:eml/dataset/abstract/para>This dataset contains the digitized treatments in Plazi based on the original journal article Szederjesi, T&#237;mea, Pavl&#237;&#269;ek, Tom&#225;s, Co&#351;kun, Y&#252;ksel, Csuzdi, Csaba (2014): New earthworm records from Turkey, with description of three new species (Oligochaeta: Lumbricidae). Zootaxa 3764 (5): 555-570, DOI: http://dx.doi.org/10.11646/zootaxa.3764.5.4</eml:eml/dataset/abstract/para><date>2014-01-01</date></data>