<data><id>480b5d0b-1488-4f30-b630-229621a200ba</id><eml:eml/dataset/title>Two new species of Corumbataia (Hypoptopomatinae: Loricariidae) from Rio Corrente, upper Rio Paran&#225; basin, Brazil</eml:eml/dataset/title><eml:eml/dataset/abstract/para>This dataset contains the digitized treatments in Plazi based on the original journal article Silva, Gabriel S. C., Roxo, Fabio F., Souza, Camila S., Oliveira, Claudio (2018): Two new species of Corumbataia (Hypoptopomatinae: Loricariidae) from Rio Corrente, upper Rio Paran&#225; basin, Brazil. Zootaxa 4483 (2): 317-330, DOI: https://doi.org/10.11646/zootaxa.4483.2.5</eml:eml/dataset/abstract/para><date>2018-01-01</date></data>