<data><id>4a525da8-1efe-4726-ba85-1997cc9d9639</id><eml:eml/dataset/title>A new species of Noblella (Anura: Craugastoridae) from the Amazonian Slopes of the Ecuadorian Andes with Comments on Noblella lochites (Lynch)</eml:eml/dataset/title><eml:eml/dataset/abstract/para>This dataset contains the digitized treatments in Plazi based on the original journal article Harvey, Michael B., Almend&#225;riz, Ana, Brito, Jorge, Batallas, Diego (2013): A new species of Noblella (Anura: Craugastoridae) from the Amazonian Slopes of the Ecuadorian Andes with Comments on Noblella lochites (Lynch). Zootaxa 3635 (1): 1-14, DOI: http://dx.doi.org/10.11646/zootaxa.3635.1.1</eml:eml/dataset/abstract/para><date>2013-01-01</date></data>