<data><id>4da5b52b-8491-4bfd-9f0d-19148c041760</id><eml:eml/dataset/title>First record of the subfamily Anoplophilinae (Orthoptera: Rhaphidophoridae) from Russia with description of a new species of the genus Alpinanoplophilus Ishikawa, 1993</eml:eml/dataset/title><eml:eml/dataset/abstract/para>This dataset contains the digitized treatments in Plazi based on the original journal article Storozhenko, Sergey Yu. (2015): First record of the subfamily Anoplophilinae (Orthoptera: Rhaphidophoridae) from Russia with description of a new species of the genus Alpinanoplophilus Ishikawa, 1993. Zootaxa 3973 (2): 391-397, DOI: http://dx.doi.org/10.11646/zootaxa.3973.2.12</eml:eml/dataset/abstract/para><date>2015-01-01</date></data>