<data><id>4dcb044d-9ed9-4321-bd40-eb5728d277e0</id><eml:eml/dataset/title>A new synonym of Neomida luteonotata (Pic, 1926) (Coleoptera: Tenebrionidae: Diaperini)</eml:eml/dataset/title><eml:eml/dataset/abstract/para>This dataset contains the digitized treatments in Plazi based on the original journal article Aloquio, Sergio, Flores, Gustavo E., Lopes-Andrade, Cristiano (2017): A new synonym of Neomida luteonotata (Pic, 1926) (Coleoptera: Tenebrionidae: Diaperini). Zootaxa 4300 (3): 438-440, DOI: https://doi.org/10.11646/zootaxa.4300.3.6</eml:eml/dataset/abstract/para><date>2017-01-01</date></data>