<data><id>5106994e-9a64-477c-8340-340b42733531</id><eml:eml/dataset/title>A revision of the subgenus Bessobates of the genus Netelia from Japan (Hymenoptera, Ichneumonidae, Tryphoninae)</eml:eml/dataset/title><eml:eml/dataset/abstract/para>This dataset contains the digitized treatments in Plazi based on the original journal article Konishi, Kazuhiko (2014): A revision of the subgenus Bessobates of the genus Netelia from Japan (Hymenoptera, Ichneumonidae, Tryphoninae). Zootaxa 3755 (4): 301-346, DOI: http://dx.doi.org/10.11646/zootaxa.3755.4.1</eml:eml/dataset/abstract/para><date>2014-01-01</date></data>