<data><id>54e48000-e28d-42b8-993e-d39b4923683f</id><eml:eml/dataset/title>Eleven new species of Sericostomatoidea from Madagascar (Trichoptera: Helicopsychidae, Petrothrincidae, Sericostomatidae)</eml:eml/dataset/title><eml:eml/dataset/abstract/para>This dataset contains the digitized treatments in Plazi based on the original journal article Johanson, Kjell Arne, Ol&#225;h, J&#225;nos (2006): Eleven new species of Sericostomatoidea from Madagascar (Trichoptera: Helicopsychidae, Petrothrincidae, Sericostomatidae). Zootaxa 1205: 1-30, DOI: 10.5281/zenodo.172376</eml:eml/dataset/abstract/para><date>2006-01-01</date></data>