<data><id>5c5304ea-13e7-4eb9-9ebf-d4d33acc5b32</id><eml:eml/dataset/title>Hexactinellida (Porifera) from the Drake Passage (Southern Ocean) with a description of three new species</eml:eml/dataset/title><eml:eml/dataset/abstract/para>This dataset contains the digitized treatments in Plazi based on the original journal article Goodwin, Claire E., Berman, Jade, Janussen, Dorte, G&#246;cke, Christian, Hendry, Katharine R. (2016): Hexactinellida (Porifera) from the Drake Passage (Southern Ocean) with a description of three new species. Zootaxa 4126 (2): 207-220, DOI: http://doi.org/10.11646/zootaxa.4126.2.2</eml:eml/dataset/abstract/para><date>2016-01-01</date></data>