<data><id>6647ca7e-cf35-4eb1-8b0c-b8756a1ba6bd</id><eml:eml/dataset/title>Marine Intertidal Phase 1 Species Dataset from the Countryside Council for Wales 1996-2005</eml:eml/dataset/title><eml:eml/dataset/abstract/para>This datasets contains species recorded as part of Countryside Council for Wales' (CCW) Phase 1 Intertidal habitat mapping survey covering all of Wales. The Intertidal mapping took place between 1996 and 2005. All work was carried out by an in-house survey team.</eml:eml/dataset/abstract/para><date>2017-11-17</date></data>