<data><id>6c573a3d-1f23-45ad-8f58-c38675fe2008</id><eml:eml/dataset/title>Type specimens of beetles (Insecta: Coleoptera) at the museo entomol&#243;gico Francisco Lu&#237;s Gallego, Medell&#237;n, Colombia</eml:eml/dataset/title><eml:eml/dataset/abstract/para>This dataset contains the digitized treatments in Plazi based on the original journal article Sep&#250;lveda-Cano, Paula A., Ram&#237;rez-Mora, Manuel A. (2009): Type specimens of beetles (Insecta: Coleoptera) at the museo entomol&#243;gico Francisco Lu&#237;s Gallego, Medell&#237;n, Colombia. Zootaxa 2017: 65-68, DOI: 10.5281/zenodo.186008</eml:eml/dataset/abstract/para><date>2009-01-01</date></data>