<data><id>6db260ab-3d8c-4152-8a7e-ad0fef402f89</id><eml:eml/dataset/title>Five new species of the genus Nannopus (Copepoda: Harpacticoida: Nannopodidae) from intertidal mudflats of the Korean West Coast (Yellow Sea)</eml:eml/dataset/title><eml:eml/dataset/abstract/para>This dataset contains the digitized treatments in Plazi based on the original journal article Vakati, Vinod, Lee Wonchoel (2017): Five new species of the genus Nannopus (Copepoda: Harpacticoida: Nannopodidae) from intertidal mudflats of the Korean West Coast (Yellow Sea). Zootaxa 4360 (1): 1-66, DOI: https://doi.org/10.11646/zootaxa.4360.1.1</eml:eml/dataset/abstract/para><date>2017-01-01</date></data>