<data><id>7d5c8ab2-3d20-46e3-b4d4-d6308bd3e5b8</id><eml:eml/dataset/title>Insectos del municipio El Carmen de Chucur&#237;, Santander - Proyecto Santander BIO</eml:eml/dataset/title><eml:eml/dataset/abstract/para>Bajo el convenio especial de cooperaci&#243;n No. 17-199 entre el departamento de Santander, la Universidad Industrial de Santander y el Instituto Alexander von Humboldt se realiz&#243; a cabo una evaluaci&#243;n biol&#243;gica y ecol&#243;gica r&#225;pida en el municipio de El Carmen de Chucur&#237; en el departamento de Santander, se realizaron muestreos de biodiversidad de diferentes grupos biol&#243;gicos, en este recurso se presentan los resultados de anfibios y reptiles. Se obtuvo un total de 243 registros biol&#243;gicos de 53 especies.</eml:eml/dataset/abstract/para><date>2019-05-23</date></data>