<data><id>8547d24d-5ff0-4946-9593-946f24086548</id><eml:eml/dataset/title>Five new species of Rohrthrips (Thysanoptera: Rohrthripidae) from Burmese amber, and the evolution of Tubulifera wings</eml:eml/dataset/title><eml:eml/dataset/abstract/para>This dataset contains the digitized treatments in Plazi based on the original journal article Ulitzka, Manfred R. (2019): Five new species of Rohrthrips (Thysanoptera: Rohrthripidae) from Burmese amber, and the evolution of Tubulifera wings. Zootaxa 4585 (1): 27-40, DOI: https://doi.org/10.11646/zootaxa.4585.1.2</eml:eml/dataset/abstract/para><date>2019-01-01</date></data>