<data><id>85e848b6-10d9-47b0-89a4-85e7e5fdc742</id><eml:eml/dataset/title>The weevil genus Trigonopterus Fauvel (Coleoptera, Curculionidae) and its synonyms&#8212;a taxonomic study on the species tied to its genus-group names</eml:eml/dataset/title><eml:eml/dataset/abstract/para>This dataset contains the digitized treatments in Plazi based on the original journal article Riedel, Alexander (2011): The weevil genus Trigonopterus Fauvel (Coleoptera, Curculionidae) and its synonyms&#8212;a taxonomic study on the species tied to its genus-group names. Zootaxa 2977: 1-49, DOI: 10.5281/zenodo.278268</eml:eml/dataset/abstract/para><date>2011-01-01</date></data>