<data><id>9554ad47-7cbe-4532-9ed2-ccd1ed179cdc</id><eml:eml/dataset/title>A taxonomic study of Muscidifurax Girault &amp; Sanders from China (Hymenoptera, Chalcidoidea, Pteromalidae)</eml:eml/dataset/title><eml:eml/dataset/abstract/para>This dataset contains the digitized treatments in Plazi based on the original journal article Xiao, Hui, Zhou, Shi-yu, Tong, Yan-feng (2018): A taxonomic study of Muscidifurax Girault &amp; Sanders from China (Hymenoptera, Chalcidoidea, Pteromalidae). ZooKeys 776: 91-103, DOI: http://dx.doi.org/10.3897/zookeys.776.25030, URL: http://dx.doi.org/10.3897/zookeys.776.25030</eml:eml/dataset/abstract/para><date>2018-01-01</date></data>