<data><id>9ea59a17-588e-4af1-8c0d-ebcd50ad0395</id><eml:eml/dataset/title>A revision of the cis-andean species of the genus Brycon M&#252;ller &amp; Troschel (Characiformes: Characidae)</eml:eml/dataset/title><eml:eml/dataset/abstract/para>This dataset contains the digitized treatments in Plazi based on the original journal article Lima, Fl&#225;vio C. T. (2017): A revision of the cis-andean species of the genus Brycon M&#252;ller &amp; Troschel (Characiformes: Characidae). Zootaxa 4222 (1): 1-189, DOI: 10.5281/zenodo.257769</eml:eml/dataset/abstract/para><date>2017-01-01</date></data>