<data><id>a54416f9-b710-4b29-9989-ad86ebfcab9e</id><eml:eml/dataset/title>Revision of the Magellanic Mactridae Lamarck, 1809 (Bivalvia: Heterodonta)</eml:eml/dataset/title><eml:eml/dataset/abstract/para>This dataset contains the digitized treatments in Plazi based on the original journal article Signorelli, Javier H., Pastorino, Guido (2011): Revision of the Magellanic Mactridae Lamarck, 1809 (Bivalvia: Heterodonta). Zootaxa 2757: 47-67, DOI: 10.5281/zenodo.201077</eml:eml/dataset/abstract/para><date>2011-01-01</date></data>