<data><id>a73d430d-a154-43c1-89fc-fe928876dbeb</id><eml:eml/dataset/title>The genus Ademon Haliday (Hymenoptera: Braconidae: Opiinae) from China, with descriptions of two new species</eml:eml/dataset/title><eml:eml/dataset/abstract/para>This dataset contains the digitized treatments in Plazi based on the original journal article Wu, Qiong, He, Jun-Hua, Chen, Xue-Xin (2014): The genus Ademon Haliday (Hymenoptera: Braconidae: Opiinae) from China, with descriptions of two new species. Zootaxa 3794 (2): 294-298, DOI: http://dx.doi.org/10.11646/zootaxa.3794.2.8</eml:eml/dataset/abstract/para><date>2014-01-01</date></data>