<data><id>b209763c-cc3a-45bc-86c1-12d2f711acea</id><eml:eml/dataset/title>Two new genera and one new species of Pantheinae from East Asia (Lepidoptera, Noctuidae: Pantheinae). Revision of Pantheinae, contribution XI</eml:eml/dataset/title><eml:eml/dataset/abstract/para>This dataset contains the digitized treatments in Plazi based on the original journal article Behounek, G., Han, H. L., Kononenko, V. S. (2015): Two new genera and one new species of Pantheinae from East Asia (Lepidoptera, Noctuidae: Pantheinae). Revision of Pantheinae, contribution XI. Zootaxa 3914 (3): 331-338, DOI: http://dx.doi.org/10.11646/zootaxa.3914.3.6</eml:eml/dataset/abstract/para><date>2015-01-01</date></data>