<data><id>b538fc74-76ff-4dbe-b9eb-8b2c341fe731</id><eml:eml/dataset/title>Biodiversidad de Mam&#237;feros de las Reservas Naturales de la Sociedad Civil del Parque Natural Regional P&#225;ramo del Duende, Valle del Cauca, Colombia</eml:eml/dataset/title><eml:eml/dataset/abstract/para>Fortalecimiento del sistema departamental de &#225;reas protegidas del Valle del Cauca (SIDAP-Valle), mediante la promoci&#243;n, establecimiento y formulaci&#243;n de planes de manejo de Reservas Naturales de la Sociedad Civil en la zona amortiguadora del Parque Regional P&#225;ramo del Duende, ubicado en los municipios de Riofr&#237;o, Trujillo y Calima, como aporte a la consolidaci&#243;n de un sistema nacional de &#225;reas protegidas de Colombia (SINAP) completo, representativo y efectivamente gestionado". Convenio 023 CVC-FEDENA</eml:eml/dataset/abstract/para><date>2019-01-11</date></data>