<data><id>bb15ffdf-3104-4e60-932b-77e650707a27</id><eml:eml/dataset/title>Brittle stars (Echinodermata: Ophiuroidea) from the continental shelf off Angola and Namibia</eml:eml/dataset/title><eml:eml/dataset/abstract/para>This dataset contains the digitized treatments in Plazi based on the original journal article Gl&#252;ck, Franziska U., St&#246;hr, Sabine, Bochert, Ralf, Zettler, Michael L. (2012): Brittle stars (Echinodermata: Ophiuroidea) from the continental shelf off Angola and Namibia. Zootaxa 3475: 1-20, DOI: 10.5281/zenodo.282230</eml:eml/dataset/abstract/para><date>2012-01-01</date></data>