<data><id>ff6a915a-43f4-4e42-b2f9-6dc5fe577d0d</id><eml:eml/dataset/title>Biodiversity monitoring in Brunswick Valley Heritage Park Mullumbimby</eml:eml/dataset/title><eml:eml/dataset/abstract/para>Brunswick Valley Heritage Park began to be planted in the 1980s by Russ and Beryl Maslen. At the time a grassy paddock along the Brunswick River it is now (2016) a young forest of trees, vines and other plants, wildlife and fungi. Two nest boxes were installed recently. Approximately 30 fungi have been observed but no one is very sure of what we have. The monitoring project, of all species, will help discover hidden treasures.</eml:eml/dataset/abstract/para><date>2019-09-25</date></data>