<data><id>oai:pangaea.de:doi:10.1594/PANGAEA.751519</id><oai_dc:dc/dc:title>Meteorological observations during PRINCIPE cruise from La Habana to La Coru&#241;a started at 1768-07-06</oai_dc:dc/dc:title><oai_dc:dc/dc:description /><oai_dc:dc/dc:subject>-, Climatological Database for the Worlds Oceans: 1750-1854, CLIWOC, Cliwoc_cruise, Comment, CT, Current direction description, Current speed description, DATE/TIME, Declination, Distance, Fog, Gusts, Hail, Identification, Landmark, LATITUDE, LONGITUDE, Precipitation/Rain, Present weather, Principe_17680706_CORREOS_274A_R4, Sea ice, Snow type, State of the sea description, Thunder, Underway cruise track measurements, Wind direction, Wind direction description, Wind force description, Wind speed</oai_dc:dc/dc:subject><date>2010-11-01</date></data>