<data><id>oai:pangaea.de:doi:10.1594/PANGAEA.199552</id><oai_dc:dc/dc:title>(Table 2) Age determination and sedimentation rates from surface sediments</oai_dc:dc/dc:title><oai_dc:dc/dc:description /><oai_dc:dc/dc:subject>Age, 14C conventional, Age, dated, BC, Biogeochemical Ocean Flux Study, BOFS, BOFS11880#5, BOFS11881#4, BOFS11882#3, BOFS11884#2, BOFS11886#4, BOFS11889#4, BOFS3C, BOFS4C, BOFS5C, BOFS7C, BOFS8C, BOFS9C, Box corer, Calculated, D184, DEPTH, sediment/rock, Discovery (1962), Elevation of event, Event label, JGOFS, Joint Global Ocean Flux Study, Latitude of event, Longitude of event, Mixing depth, Northeast Atlantic, Sedimentation rate</oai_dc:dc/dc:subject><date>1993-02-23</date></data>