<data><id>oai:pangaea.de:doi:10.1594/PANGAEA.816018</id><oai_dc:dc/dc:title>(Table 1) Density of seabirds (Fulmarus glacialis, Rissa tridactyla, Larus hyperboreus, Sterna paradisaea, and Stercorarius parasiticus) in Allen Bay 2010</oai_dc:dc/dc:title><oai_dc:dc/dc:description /><oai_dc:dc/dc:subject>Allen_Bay, Area extent, Aves, Cornwallis Island, Nunavut, Canada, DATE/TIME, Date/time end, Distance, Fulmarus glacialis, density, Larus hyperboreus, density, Location, Number, OBSE, Observation, Rissa tridactyla, density, Sample amount, Speed, Stercorarius parasiticus, density, Sterna paradisaea, density</oai_dc:dc/dc:subject><date>2012-06-25</date></data>