<data><id>oai:pangaea.de:doi:10.1594/PANGAEA.251105</id><oai_dc:dc/dc:title>Paleontology age profile (datum list) of ODP Hole 182-1134A</oai_dc:dc/dc:title><oai_dc:dc/dc:description /><oai_dc:dc/dc:subject>182-1134A, AGE, Age, maximum/old, Age, minimum/young, Ageprofile Datum Description, Depth, bottom/max, DEPTH, sediment/rock, Depth, top/min, DRILL, Drilling/drill rig, Great Australian Bight, Joides Resolution, Leg182, Ocean Drilling Program, ODP</oai_dc:dc/dc:subject><date>2005-02-23</date></data>