<data><id>oai:pangaea.de:doi:10.1594/PANGAEA.772552</id><oai_dc:dc/dc:title>Hydrochemistry measured on water bottle samples during cruise TI73</oai_dc:dc/dc:title><oai_dc:dc/dc:description /><oai_dc:dc/dc:subject>1, 10, 11, 12, 13, 14, 15, 16, 17, 18, 19, 2, 20, 21, 22, 2-2, 2-3, 2-4, 2-5, 2-6, 2-7, 2-8, 3, 4, 5, 6, 7, 8, 9, Alkalinity, total, Bottle, Niskin, Date/Time of event, DEPTH, water, Elevation of event, Event label, HCAAO_15280, HCAAO_15281, HCAAO_15282, HCAAO_15283, HCAAO_15284, HCAAO_15285, HCAAO_15286, HCAAO_15287, HCAAO_15288, HCAAO_15289, HCAAO_15290, HCAAO_15291, HCAAO_15292, HCAAO_15293, HCAAO_15294, HCAAO_15295, HCAAO_15296, HCAAO_15297, HCAAO_15298, HCAAO_15299, HCAAO_15300, HCAAO_15301, HCAAO_15302, HCAAO_15303, HCAAO_15304, HCAAO_15305, HCAAO_15306, HCAAO_15307, HCAAO_15308, HCAAO_15309, HCAAO_15310, HCAAO_15311, HCAAO_15312, HCAAO_15313, HCAAO_15314, HCAAO_15315, HCAAO_15316, HCAAO_15317, HCAAO_15318, HCAAO_15319, HCAAO_15320, HCAAO_15321, HCAAO_15322, HCAAO_15323, HCAAO_15324, HCAAO_15325, HCAAO_15326, HCAAO_15327, HCAAO_15328, HCAAO_15329, HCAAO_15330, HCAAO_15331, HCAAO_15332, HCAAO_15333, HCAAO_15334, HCAAO_15335, HCAAO_15336, HCAAO_15337, HCAAO_15338, HCAAO_15339, HCAAO_15340, HCAAO_15341, HCAAO_15342, HCAAO_15343, HCAAO_15344, HCAAO_15345, HCAAO_15346, HCAAO_15347, HCAAO_15348, HCAAO_15349, HCAAO_15350, HCAAO_15351, HCAAO_15352, HCAAO_15353, HCAAO_15354, HCAAO_15355, HCAAO_15356, HCAAO_15357, HCAAO_15358, HCAAO_15359, HCAAO_15360, HCAAO_15361, HCAAO_15362, HCAAO_15363, HCAAO_15364, HCAAO_15365, HCAAO_15366, HCAAO_15367, HCAAO_15368, HCAAO_15369, HCAAO_15370, HCAAO_15371, HCAAO_15372, HCAAO_15373, HCAAO_15374, HCAAO_15375, HCAAO_15376, HCAAO_15377, HCAAO_15378, HCAAO_15379, HCAAO_15380, HCAAO_15381, HCAAO_15382, HCAAO_15383, HCAAO_15384, HCAAO_15385, HCAAO_15386, HCAAO_15387, HCAAO_15388, Laptev Sea, Latitude of event, Longitude of event, NIS, Nitrite, Oxygen, pH, Phosphate, Silicate, TI73</oai_dc:dc/dc:subject><date>2001-12-09</date></data>