<data><id>oai:pangaea.de:doi:10.1594/PANGAEA.132313</id><oai_dc:dc/dc:title>Primary production at station NBP97-01-01-10</oai_dc:dc/dc:title><oai_dc:dc/dc:description /><oai_dc:dc/dc:subject>01132347, AESOPS, Antarctic Environments Southern Ocean Process Study, Bottle number, Calculated, Carbon assimilation per unit chl-a from dawn to dusk (24 hr.), CTD/Rosette, CTD-RO, DEPTH, water, JGOFS, Joint Global Ocean Flux Study, Nathaniel B. Palmer, NBP97-01, NBP97-01-01-10, Primary production, carbon assimilation (24 hr.), Southern Ocean</oai_dc:dc/dc:subject><date>2003-11-27</date></data>