<data><id>oai:pangaea.de:doi:10.1594/PANGAEA.815274</id><oai_dc:dc/dc:title>(Table 5a) Chemical composition of natural swamp waters of the Lower Tom' Basin</oai_dc:dc/dc:title><oai_dc:dc/dc:description /><oai_dc:dc/dc:subject>Archive of Ocean Data, ARCOD, Arsenic, Cadmium, Copper, Event label, Latitude of event, Lead, Lithium, Longitude of event, LTB-149, LTB-152, LTB-153, LTB-162, LTB-173, LTB-178, LTB-179, LTB-186, LTB-3, LTB-4, LTB-81, LTB-82, LTB-88, LTB-939, Manganese, Sample code/label, Sample type, Voltammetry, Water sample, Western Siberia, WS, Zinc</oai_dc:dc/dc:subject><date>2012-06-06</date></data>