<data><id>oai:pangaea.de:doi:10.1594/PANGAEA.863023</id><oai_dc:dc/dc:title>Modal grain-sizes of Saharan dust in the Atlantic Ocean measured in surface sediments from October 2012 to November 2013</oai_dc:dc/dc:title><oai_dc:dc/dc:description /><oai_dc:dc/dc:subject>13M1, 13M2, 13M3, 13M4, 13M5, Calculated, DEPTH, sediment/rock, Elevation of event, Event label, Latitude of event, Longitude of event, Mode, grain size, Mooring (long time), MOORY, North Atlantic Ocean</oai_dc:dc/dc:subject><date>2016-07-14</date></data>