<data><id>oai:pangaea.de:doi:10.1594/PANGAEA.815294</id><oai_dc:dc/dc:title>(Table 1) Distribution of middle Eocene calcareous nannofossils in sediment cores 16-43, 16-44, and 16-4</oai_dc:dc/dc:title><oai_dc:dc/dc:description /><oai_dc:dc/dc:subject>Blackites spinosus, Calcidiscus leptoporus, Chiasmolithus expansus, Chiasmolithus grandis, Chiasmolithus solitus, Clausicoccus fenestratus, Coccolithus formosus, Coccolithus pelagicus, Coccolithus sp., Coccolithus staurion, DEPTH, sediment/rock, Discoaster barbadiensis, Discoaster bifax, Discoaster binodosus, Discoaster distinctus, Discoaster saipanensis, Elevation of event, Ellipsolithus distichus, Event label, Helicosphaera carteri, IO1678, IO1678.043-PC, IO1678.044-PC, IO1678.046-PC, Islas Orcadas, Latitude of event, Longitude of event, Markalius inversus, Nannofossil abundance, Nannofossils preservation, Nannofossil zone, Neococcolithes dubius, PC, Piston corer, Pontosphaera pectinata, Pontosphaera plana, Pontosphaera pulcheroides, Reticulofenestra, Reticulofenestra bisecta bisecta, Reticulofenestra onusta, Reticulofenestra samodurovii, Reticulofenestra sp., Reticulofenestra umbilicus, Sample code/label, Sphenolithus moriformis, Zygrhablithus bijugatus</oai_dc:dc/dc:subject><date>1983-06-06</date></data>