<data><id>oai:pangaea.de:doi:10.1594/PANGAEA.131712</id><oai_dc:dc/dc:title>Bulk sedimentology of core PS2674-1</oai_dc:dc/dc:title><oai_dc:dc/dc:description /><oai_dc:dc/dc:subject>ANT-XII/4, AWI_Paleo, Calcium carbonate, Calculated, Calculated from weight/volume, Calculated from wet bulk density, Carbon, organic, total, Density, Density, dry bulk, Density, grain, Density, wet bulk, DEPTH, sediment/rock, Element analyser CHN, LECO, Gravity corer (Kiel type), Paleoenvironmental Reconstructions from Marine Sediments @ AWI, Polarstern, Porosity, PS2674-1, PS35/054, PS35 06AQANTXII_4, Pycnometer (Micromeritics), SL, Southeast Pacific, Water content, wet mass</oai_dc:dc/dc:subject><date>2003-11-26</date></data>