<data><id>oai:pangaea.de:doi:10.1594/PANGAEA.250070</id><oai_dc:dc/dc:title>Crinoidea abundance of Hole 11-100</oai_dc:dc/dc:title><oai_dc:dc/dc:description /><oai_dc:dc/dc:subject>11-100, Abundance estimate, Deep Sea Drilling Project, DEPTH, sediment/rock, DRILL, Drilling/drill rig, DSDP, Glomar Challenger, Leg11, North Atlantic/BASIN, ODP sample designation, Saccocoma quenstedti, Saccocoma schattenbergi, Saccocoma sp., Saccocoma subornata, Sample code/label</oai_dc:dc/dc:subject><date>2005-02-17</date></data>