<data><id>oai:pangaea.de:doi:10.1594/PANGAEA.786621</id><oai_dc:dc/dc:title>(Table 2) Population density and zoobenthos biomass in bottom communities of the Novosibirsk Polynya in September 2008</oai_dc:dc/dc:title><oai_dc:dc/dc:description /><oai_dc:dc/dc:subject>Archive of Ocean Data, ARCOD, BARKALAV-2008-1, BARKALAV-2008-10, BARKALAV-2008-11, BARKALAV-2008-2, BARKALAV-2008-3, BARKALAV-2008-4, BARKALAV-2008-5, BARKALAV-2008-6, BARKALAV-2008-7, BARKALAV-2008-8, BARKALAV-2008-9, Benthos, East Siberian Sea, Elevation of event, Event label, Laptev Sea, Latitude of event, Longitude of event, MULT, Multiple investigations, Zoobenthos, Zoobenthos, biomass</oai_dc:dc/dc:subject><date>2011-07-27</date></data>