<data><id>oai:pangaea.de:doi:10.1594/PANGAEA.897956</id><oai_dc:dc/dc:title>ARM intensity/magnetic susceptibility ratio of the Miocene section of ANDRILL AND-2A drill core</oai_dc:dc/dc:title><oai_dc:dc/dc:description /><oai_dc:dc/dc:subject>AND-2A, ANDRILL, Antarctica, Antarctic Geological Drilling, ARM intensity/magnetic susceptibility ratio, DEPTH, sediment/rock, DRILL, Drilling/drill rig, Early Miocene, magnetic properties, Magnetometer, McMurdo Sound, McMurdo Station, Ross Sea, SMS, Southern McMurdo Sound, volcanoes</oai_dc:dc/dc:subject><date>2019-01-31</date></data>