<data><id>oai:pangaea.de:doi:10.1594/PANGAEA.415613</id><oai_dc:dc/dc:title>Meteorological observations during CHOFU MARU cruise 49TU9207_1</oai_dc:dc/dc:title><oai_dc:dc/dc:description /><oai_dc:dc/dc:subject>49TU9207_1, 49TU9207_1-track, ALTITUDE, Aneroid barometer, Chofu Maru, Cloud base height, CT, DATE/TIME, Dew/frost point, Dew point hygrometer, High cloud, LATITUDE, LONGITUDE, Low/middle cloud amount, Low cloud, Middle cloud, Platinum resistance thermometer (PRT), Pressure, atmospheric, Temperature, air, Temperature, air, wet bulb, Temperature, water, Total cloud amount, Underway cruise track measurements, Visual observation, Wind direction, Wind monitor, Wind speed, WOCE, World Ocean Circulation Experiment</oai_dc:dc/dc:subject><date>2006-04-12</date></data>