<data><id>oai:v1.datadryad.org:10255/dryad.195216</id><oai_dc:dc/dc:title>Variant_abundance_gen150</oai_dc:dc/dc:title><oai_dc:dc/dc:description>Frequency of the cycloserine resistant and sensitive variants in each subpopulation after 150 generations of evolution in environments with varying degrees of spatial structure.</oai_dc:dc/dc:description><oai_dc:dc/dc:subject>Community: structure|Ecology: microbial|Ecology: spatial|Evolution: experimental|Bacteria|Spatial Structure</oai_dc:dc/dc:subject><date
>2018-10-17T05:31:12Z</date
></data>