<data><id>oai:v1.datadryad.org:10255/dryad.143760</id><oai_dc:dc/dc:title>Data for Experiment 2</oai_dc:dc/dc:title><oai_dc:dc/dc:description>This is the data for the Experiment 2 for the manuscript &#8220;Secondary compounds from exotic tree plantations change female mating preferences in the palmate newt (Lissotriton helveticus)&#8221;. Data was collected by MIC and CC. All methods are described in the associated manuscript. Column headings are described in the excel spreadsheet.</oai_dc:dc/dc:description><oai_dc:dc/dc:subject>anthropogenic disturbance|female choice|Lissotriton helveticus|sexual selection|Urodeles</oai_dc:dc/dc:subject><date
>2017-04-19T19:02:08Z</date
></data>