<data><id>oai:v1.datadryad.org:10255/dryad.166884</id><oai_dc:dc/dc:title>Shapes files of forest fragments in the Eastern Arc Mountains</oai_dc:dc/dc:title><oai_dc:dc/dc:description>Forest fragments containing native forest &#8805;10 ha in size and with &#8805;50% tree cover in 13 Eastern Arc Mountains located in Tanzania and Kenya.</oai_dc:dc/dc:description><oai_dc:dc/dc:subject>Fragment Size and Number|Forest Cover|Kenya|Tanzania</oai_dc:dc/dc:subject><date
>2018-01-17T19:23:06Z</date
></data>